[
  { "title": "민감정보 차단", "emoji": "🚫", "desc": "학생 개인정보, 성적 원본, 환자정보는 AI에게 넘기지 않기" },
  { "title": "외부전송 확인", "emoji": "📤", "desc": "이메일, SNS, 배포 등 밖으로 나가는 행동은 사람 확인 후 실행" },
  { "title": "API 키 관리", "emoji": "🔑", "desc": ".env, openclaw.json 외부 노출 금지. 월 1회 점검" },
  { "title": "실행권한 인식", "emoji": "⚠️", "desc": "파일 삭제는 trash 우선. 의도치 않은 명령 주의" },
  { "title": "프롬프트 인젝션 방어", "emoji": "🛡️", "desc": "indirect-prompt-injection 스킬 설치. 외부 콘텐츠 검증" },
  { "title": "디스크 암호화", "emoji": "💿", "desc": "BitLocker(윈도우) + FileVault(맥미니) 확인" }
]
